{"preRemediationSizeMB":71.87,"totalSizeMB":71.87,"remediated":false,"topOffenderApp":"C:\\Windows\\System32\\drivers\\Intel\\ICPS\\IntelConnectivityNetworkService.exe","remediateFlag":false,"computerName":"MAXWELL-LEASE2","status":"GREEN","folderExists":true,"topOffenders":[{"app":"C:\\Windows\\System32\\drivers\\Intel\\ICPS\\IntelConnectivityNetworkService.exe","hits":360143,"accessType":"location"},{"app":"C:\\Windows\\System32\\drivers\\Intel\\ICPS\\IntelConnect.exe","hits":234154,"accessType":"location"},{"app":"C:\\Windows\\System32\\svchost.exe","hits":1247,"accessType":"location"},{"app":"MicrosoftWindows.Client.WebExperience_cw5n1h2txyewy","hits":253,"accessType":"location"},{"app":"C:\\Windows\\System32\\drivers\\Intel\\ICPS\\IDBWM.exe","hits":62,"accessType":"location"},{"app":"MSTeams_8wekyb3d8bbwe","hits":19,"accessType":"location"},{"app":"C:\\Program Files\\Adobe\\Acrobat DC\\Acrobat\\AcroCEF\\AcroCEF.exe","hits":10,"accessType":"location"},{"app":"C:\\Program Files (x86)\\Microsoft\\Edge\\Application\\msedge.exe","hits":8,"accessType":"location"}],"osBuild":"26100","osVersion":"Microsoft Windows 11 Pro","topOffenderHits":360143,"propertyName":"","files":[{"path":"C:\\ProgramData\\Microsoft\\Windows\\CapabilityAccessManager\\CapabilityAccessManager.db","lastWrite":"2026-04-20 22:02:13","name":"CapabilityAccessManager.db","sizeMB":23.65},{"path":"C:\\ProgramData\\Microsoft\\Windows\\CapabilityAccessManager\\CapabilityAccessManager.db-shm","lastWrite":"2026-04-20 22:02:13","name":"CapabilityAccessManager.db-shm","sizeMB":0.22},{"path":"C:\\ProgramData\\Microsoft\\Windows\\CapabilityAccessManager\\CapabilityAccessManager.db-wal","lastWrite":"2026-04-21 12:36:31","name":"CapabilityAccessManager.db-wal","sizeMB":46.86},{"path":"C:\\ProgramData\\Microsoft\\Windows\\CapabilityAccessManager\\CapabilityConsentStorage.db","lastWrite":"2026-04-20 14:01:55","name":"CapabilityConsentStorage.db","sizeMB":1},{"path":"C:\\ProgramData\\Microsoft\\Windows\\CapabilityAccessManager\\CapabilityConsentStorage.db-shm","lastWrite":"2026-04-20 22:02:13","name":"CapabilityConsentStorage.db-shm","sizeMB":0.03},{"path":"C:\\ProgramData\\Microsoft\\Windows\\CapabilityAccessManager\\CapabilityConsentStorage.db-wal","lastWrite":"2026-04-20 14:01:55","name":"CapabilityConsentStorage.db-wal","sizeMB":0.11}],"statusLabel":"Healthy (71.87 MB)","scanTime":"2026-04-21 12:36:32","offenderScanTime":"2026-04-21 12:36:32"}